pyuhoods/__init__.py
pyuhoods/api.py
pyuhoods/cli.py
pyuhoods/client.py
pyuhoods/consts.py
pyuhoods/device.py
pyuhoods/endpoints.py
pyuhoods/errors.py
pyuhoods/util.py
pyuhoods-0.0.21.dist-info/entry_points.txt
pyuhoods-0.0.21.dist-info/LICENSE
pyuhoods-0.0.21.dist-info/WHEEL
pyuhoods-0.0.21.dist-info/METADATA
pyuhoods-0.0.21.dist-info/RECORD
